Metadata-Version: 1.1
Name: microfs
Version: 1.2.3
Summary: A module and utility to work with the simple filesystem on the BBC micro:bit
Home-page: https://github.com/ntoll/microfs
Author: Nicholas H.Tollervey
Author-email: ntoll@ntoll.org
License: MIT
Platform: UNKNOWN
Classifier: Development Status :: 4 - Beta
Classifier: Environment :: Console
Classifier: Intended Audience :: Developers
Classifier: Intended Audience :: Education
Classifier: License :: OSI Approved :: MIT License
Classifier: Operating System :: POSIX
Classifier: Operating System :: Microsoft :: Windows
Classifier: Programming Language :: Python :: 2.7
Classifier: Programming Language :: Python :: 3.3
Classifier: Topic :: Education
Classifier: Topic :: Software Development :: Embedded Systems
